complex_library/__init__.py
complex_library/complex_functions.py
complex_library/second_script.py
bollettinotest-0.0.1.dist-info/METADATA
bollettinotest-0.0.1.dist-info/WHEEL
bollettinotest-0.0.1.dist-info/top_level.txt
bollettinotest-0.0.1.dist-info/RECORD
